fitna/__init__.py
fitna/data.py
fitna/em.py
fitna/plotly.py
fitna-0.0.3.dist-info/LICENSE.txt
fitna-0.0.3.dist-info/METADATA
fitna-0.0.3.dist-info/WHEEL
fitna-0.0.3.dist-info/top_level.txt
fitna-0.0.3.dist-info/RECORD
