Metadata-Version: 2.1
Name: fitna
Version: 0.0.3
Summary: Data fitting algorithms
Home-page: https://github.com/plexoos/toufy
Author: Dmitri Smirnov
Author-email: dmixsmi@gmail.com
License: UNKNOWN
Platform: UNKNOWN
Classifier: Programming Language :: Python :: 3
Classifier: Operating System :: OS Independent
Classifier: Topic :: Scientific/Engineering
